<?xml version="1.0" encoding="UTF-8"?>
<CONFIG>
    <DATA_UI>
      <TITLE_HOME>系统首页</TITLE_HOME>
      <TITLE_WORKFLOW>工作流</TITLE_WORKFLOW> 
        <TITLE_CMS>内容管理</TITLE_CMS>
        <TITLE_FAVORITE>收藏夹</TITLE_FAVORITE>
        <TITLE_SYSTEM_FUNC>系统功能</TITLE_SYSTEM_FUNC>
        <TITLE_SYSTEM>系统管理</TITLE_SYSTEM>
        <TITLE_TOOLS>工具</TITLE_TOOLS>
        <TITLE_HELP>帮助</TITLE_HELP>
        <TITLE_EXIT>退出</TITLE_EXIT>
        <TITLE_MENU_YINGSHOU>应收款统计</TITLE_MENU_YINGSHOU>
        <TITLE_MENU_YINGFU>应付款统计</TITLE_MENU_YINGFU>
        <TITLE_MENU_DEP>部门管理</TITLE_MENU_DEP>
        <TITLE_MENU_RIGHT>权限管理</TITLE_MENU_RIGHT>
		    <TITLE_MENU_DOMAIN>同步域用户</TITLE_MENU_DOMAIN>
        <TITLE_MENU_EMP>人员管理</TITLE_MENU_EMP>
	      <TITLE_MENU_ONLINEUSER>在线用户管理</TITLE_MENU_ONLINEUSER>
        <TITLE_MENU_RES>资源管理</TITLE_MENU_RES>
        <TITLE_MENU_BIZALLOT>业务分帐</TITLE_MENU_BIZALLOT>
        <TITLE_MENU_LOG>日志管理</TITLE_MENU_LOG>
        <TITLE_MENU_EMAIL_CONFIG>邮件服务器配置</TITLE_MENU_EMAIL_CONFIG>
        <TITLE_MENU_CLIENT_CODE>客户编码</TITLE_MENU_CLIENT_CODE>
        <TITLE_MENU_SYS_OPTION>系统选项</TITLE_MENU_SYS_OPTION>
        <TITLE_MENU_USER_MANUAL>用户使用手册</TITLE_MENU_USER_MANUAL>
        <TITLE_MENU_SYSTEM_MANUAL>系统管理手册</TITLE_MENU_SYSTEM_MANUAL>
        <TITLE_MENU_PRODCODE>产品码</TITLE_MENU_PRODCODE>
        <TITLE_MENU_LICCODE>用户许可码</TITLE_MENU_LICCODE>
        <TITLE_MENU_ABOUT>关于本系统</TITLE_MENU_ABOUT>
        <TITLE_MENU_EDIT_PASS>修改密码</TITLE_MENU_EDIT_PASS>
        <TITLE_MENU_EDIT_PROFILE>修改用户信息</TITLE_MENU_EDIT_PROFILE>
        <TITLE_MENU_GETLOG>提取系统日志</TITLE_MENU_GETLOG>
        <TITLE_LOGINUSER>登录用户</TITLE_LOGINUSER>
        <TREE_DAILYWORK>收藏夹</TREE_DAILYWORK>
        <CONT_MNU_REC>记录操作</CONT_MNU_REC>
        <CONT_MNU_DOC>文档操作</CONT_MNU_DOC>
        <CONT_MNU_RESACTION>资源操作</CONT_MNU_RESACTION>
        <CONT_MNU_EXT>扩展功能</CONT_MNU_EXT>
        <CONT_MNU_SEARCH>查询统计</CONT_MNU_SEARCH>
        <CONT_MNU_SEARCH_START>开始查询</CONT_MNU_SEARCH_START>
        <CONT_MNU_SEARCH_AGAIN>再次查询</CONT_MNU_SEARCH_AGAIN>
        <CONT_MNU_SEARCH_FTABLE>全表查询</CONT_MNU_SEARCH_FTABLE>
		<CONT_MNU_SEARCH_ADVANCED>高级查询</CONT_MNU_SEARCH_ADVANCED>
        <CONT_MNU_SEARCH_CANCEL>取消查询</CONT_MNU_SEARCH_CANCEL>
        <CONT_REC_NUM>总数</CONT_REC_NUM>
        <TITLE_STATISTICS>列表统计</TITLE_STATISTICS>
        <TITLE_FORMULA>计算公式</TITLE_FORMULA>
        <TITLE_GENERAL_ROWFILTER>通用行过滤</TITLE_GENERAL_ROWFILTER>
        <TITLE_PERSONAL_ROWFILTER>个人行过滤</TITLE_PERSONAL_ROWFILTER>
      <!-- <TITLE_BATCH_SEND>邮件短信群发</TITLE_BATCH_SEND>-->
        <TITLE_SYSFUNC_SEARCHDOC>搜索文档</TITLE_SYSFUNC_SEARCHDOC>
        <TITLE_UPDATE_DATABASE>数据库升级</TITLE_UPDATE_DATABASE>
        <TITLE_MAINTAIN_DATABASE>系统维护</TITLE_MAINTAIN_DATABASE>
        <TITLE_UPDATE_SYSTEM>系统配置升级</TITLE_UPDATE_SYSTEM>
        <TITLE_SYSTEM_DEBUG>系统调试</TITLE_SYSTEM_DEBUG>
        <TITLE_RECORD_SAVE>保存</TITLE_RECORD_SAVE>
        <TITLE_RECORD_PRINT>打印</TITLE_RECORD_PRINT>
        <TITLE_RECORD_NEW>新建</TITLE_RECORD_NEW>
        <TITLE_RECORD_EXIT>退出</TITLE_RECORD_EXIT>
        <TITLE_RECORD_EXT>扩展功能</TITLE_RECORD_EXT>
        <TITLE_RECORD_SAVENEW>保存并新建</TITLE_RECORD_SAVENEW>
        <TITLE_RECORD_STATUS_ADD>新增状态</TITLE_RECORD_STATUS_ADD>
        <TITLE_RECORD_STATUS_EDIT>修改状态</TITLE_RECORD_STATUS_EDIT>
        <TITLE_RECORD_STATUS_VIEW>查阅状态</TITLE_RECORD_STATUS_VIEW>
        <TITLE_CMD_ADD>添加</TITLE_CMD_ADD>
        <TITLE_CMD_EDIT>修改</TITLE_CMD_EDIT>
        <TITLE_CMD_VIEW>查阅</TITLE_CMD_VIEW>
        <TITLE_CMD_DEL>删除</TITLE_CMD_DEL>
        <TITLE_CMD_SAVE>保存</TITLE_CMD_SAVE>
        <TITLE_CMD_REFRESH>刷新</TITLE_CMD_REFRESH>
      <TITLE_CONFIRM>确认</TITLE_CONFIRM>
      <TITLE_CANCEL>取消</TITLE_CANCEL>
      <RES_USERMGR>人员管理</RES_USERMGR>
		<CONT_VIEW_EDIT>修改</CONT_VIEW_EDIT>
		<CONT_VIEW_DELETE>删除</CONT_VIEW_DELETE>
    </DATA_UI>
    <DATA_MSG>
        <ERR_UNKNOWN>操作异常失败！</ERR_UNKNOWN>
        <TIP_ADDDOC_LATER>您没有上传文档，以后请用文档操作菜单中的签入文档来为此条记录添加文档！!!!!</TIP_ADDDOC_LATER>
        <ERR_COMM_SAVEFILE>保存待发送邮件的附件时异常出错！</ERR_COMM_SAVEFILE>
        <TIP_COMM_EMAILSUCC>邮件发送成功！</TIP_COMM_EMAILSUCC>
        <ERR_COMM_EMAILFAIL>邮件发送失败，请检验本系统邮件服务器配置中的SMTP服务器和邮件发送校验帐号和密码的设置信息是否正确！</ERR_COMM_EMAILFAIL>
        <TIP_COMM_SMSSUCC>短信发送成功！</TIP_COMM_SMSSUCC>
        <ERR_COMM_SMSFAIL>短信发送失败，请检验GSM Modem短信发送硬件设备是否正确连接在本系统服务器的串口上！</ERR_COMM_SMSFAIL>
        <ERR_COMM_SMSFAILED_PHONES>以下手机号码的短信发送失败：</ERR_COMM_SMSFAILED_PHONES>
        <RECORD_OPARATE>当前操作需要先选择有效的记录。</RECORD_OPARATE>
        <RECORD_DELETE>确定要删除当前选中的记录吗？</RECORD_DELETE>
        <VIEW_DOCUMENT>该文件类型不支持在线浏览</VIEW_DOCUMENT>
        <RECORD_PRINT>打印窗体不存在，请先为本资源设计打印窗体！</RECORD_PRINT>
        <SEARCH_MSG>搜索条件无效，请重新设置搜索条件！</SEARCH_MSG>
        <NEW_RECORD>新建记录失败，请检查数据库链接！</NEW_RECORD>
        <DELETE_DOCUMENT>删除文档失败！文档路径：</DELETE_DOCUMENT>
    </DATA_MSG>
    <DATA_NOTES>
        <NOTES_PRODCODE_EXPIRE DESC="发现产品码过期后的界面内容"><![CDATA[
			本软件系统的产品码已过期，在没有输入有效的用户许可码的情况下，产品码可以允许系统正常运行12个月，且默认20个用户许可数。现在产品码已过期，请输入购买正版软件时随盘附带的用户许可码。如果没有，请向软件厂商购买用户许可数，以便系统能继续正常运行。用户许可数是指人员管理中可添加的用户登录帐号数量。		]]></NOTES_PRODCODE_EXPIRE>
        <NOTES_PRODCODE_INTRODUCE DESC="产品码介绍"><![CDATA[
			产品码是企业数据流系统的唯一标识代码，格式为20位数字，一般可以在正版软件的CD包装盒内或CD盘上找到。在系统第一次使用时必须输入产品码。		]]></NOTES_PRODCODE_INTRODUCE>
        <NOTES_LICCODE_INTRODUCE DESC="用户许可码介绍"><![CDATA[
			用户许可码是企业数据流系统的用户数量的代码，即系统可创建的用户登录帐号的数量。格式为20位数字。在购买正版软件时随盘附带。请在安装企业数据流系统成功后输入用户许可码。如果安装系统后没有输入用户许可码，系统的默认用户许可数为20个，系统仍然能正常使用，但有效期为12个月，到期后系统会提示输入用户许可码。用户许可码与产品码一一对应，如果遗失用户许可码，请向软件厂商或经销商索取。			
			如果系统当前的用户许可数不能满足您企业的需求时，请向软件厂商购买用户许可码。		]]></NOTES_LICCODE_INTRODUCE>
    </DATA_NOTES>
</CONFIG>
